industrial_model_client_generator/__init__.py
industrial_model_client_generator/config.py
industrial_model_client_generator/constants.py
industrial_model_client_generator/generator.py
industrial_model_client_generator/helpers.py
industrial_model_client_generator/models.py
industrial_model_client_generator/py.typed
industrial_model_client_generator/templates/__init__.j2
industrial_model_client_generator/templates/clients_async.j2
industrial_model_client_generator/templates/clients_facade.j2
industrial_model_client_generator/templates/clients_sync.j2
industrial_model_client_generator/templates/models_aggregation.j2
industrial_model_client_generator/templates/models_entity.j2
industrial_model_client_generator/templates/models_entity_complete.j2
industrial_model_client_generator/templates/models_search.j2
industrial_model_client_generator/templates/requests_aggregation.j2
industrial_model_client_generator/templates/requests_base.j2
industrial_model_client_generator/templates/requests_query.j2
industrial_model_client_generator/templates/requests_search.j2
industrial_model_client_generator-0.1.7.dist-info/METADATA
industrial_model_client_generator-0.1.7.dist-info/WHEEL
industrial_model_client_generator-0.1.7.dist-info/RECORD
