Metadata-Version: 2.4
Name: industrial-model-client-generator
Version: 0.1.7
Summary: Industrial Model Client Generator
Author-email: Lucas Alves <lucasrosaalves@gmail.com>
Classifier: Programming Language :: Python
Classifier: Programming Language :: Python :: 3
Classifier: Programming Language :: Python :: 3 :: Only
Classifier: Programming Language :: Python :: 3.11
Classifier: Programming Language :: Python :: 3.12
Classifier: Programming Language :: Python :: 3.13
Classifier: Topic :: Database
Classifier: Topic :: Database :: Database Engines/Servers
Classifier: Typing :: Typed
Requires-Python: >=3.11
Requires-Dist: cognite-sdk>=7.75.0
Requires-Dist: dotenv>=0.9.9
Requires-Dist: industrial-model>=0.1.31
Requires-Dist: jinja2>=3.1.6
Requires-Dist: mypy>=1.15.0
Requires-Dist: pydantic>=2.11.4
Requires-Dist: pyyaml>=6.0.2
Requires-Dist: ruff>=0.11.8
